{
    "cookers": [
       {
        "name": "Повар 1",
        "id": 1,
        "cookItems": [  {
           "name": "солянка",
           "id": 1

        }, {
            "name": "борщ",
            "id": 2
        }, {
            "name": "салатик",
            "id": 2
        } ]

       },
       {
        "name": "Повар 2",
        "id": 1,
        "cookItems": [  {
           "name": "морковка",
           "id": 1

        }, {
            "name": "щи",
            "id": 2
        }, {
            "name": "огурец",
            "id": 2
        } ]

       },
       {
        "name": "Повар 3",
        "id": 1,
        "cookItems": [  
            {
           "name": "масло",
           "id": 1
        }, {
            "name": "шашлыки",
            "id": 2
        }, {
            "name": "стейк-нью йорк",
            "id": 2
        } ]
       }
    ]
}